IoT_pki/__init__.py
IoT_pki/admin.py
IoT_pki/apps.py
IoT_pki/forms.py
IoT_pki/helper_functions.py
IoT_pki/models.py
IoT_pki/permissions.py
IoT_pki/serializers.py
IoT_pki/tests.py
IoT_pki/urls.py
IoT_pki/views.py
IoT_pki/x509_functions.py
IoT_pki/migrations/0001_initial.py
IoT_pki/migrations/0002_auto_20170711_1548.py
IoT_pki/migrations/__init__.py
IoT_pki/templates/IoT_pki/new_ca.html
IoT_pki/templates/IoT_pki/pki_index.html
django_IoT_pki-1.4.dist-info/DESCRIPTION.rst
django_IoT_pki-1.4.dist-info/METADATA
django_IoT_pki-1.4.dist-info/RECORD
django_IoT_pki-1.4.dist-info/WHEEL
django_IoT_pki-1.4.dist-info/metadata.json
django_IoT_pki-1.4.dist-info/top_level.txt
zibawa_PKI/__init__.py
zibawa_PKI/settings-sample.py
zibawa_PKI/settings.py
zibawa_PKI/urls.py
zibawa_PKI/wsgi.py
