Metadata-Version: 2.0
Name: django-IoT-pki
Version: 1.4
Summary: A simple public key infrastructure to allow issuing and automatic renewal of X509 certificates
Home-page: https://www.zibawa.com/
Author: Matt Field
Author-email: matt.field@zibawa.com
License: GNU license
Platform: UNKNOWN
Classifier: Environment :: Web Environment
Classifier: Framework :: Django
Classifier: Framework :: Django :: 1.11
Classifier: Intended Audience :: Developers
Classifier: License :: OSI Approved :: GNU General Public License v3 (GPLv3)
Classifier: Operating System :: OS Independent
Classifier: Programming Language :: Python
Classifier: Programming Language :: Python :: 3
Classifier: Programming Language :: Python :: 3.4
Classifier: Programming Language :: Python :: 3.5
Classifier: Topic :: Internet :: WWW/HTTP
Classifier: Topic :: Internet :: WWW/HTTP :: Dynamic Content
Classifier: Topic :: Security :: Cryptography
Requires-Dist: coreapi
Requires-Dist: cryptography
Requires-Dist: djangorestframework
Requires-Dist: markdown
Requires-Dist: pyOpenSSL
